markdowntweetembed/__init__.py
markdowntweetembed/tweetembed.py
markdowntweetembed-0.1.dist-info/METADATA
markdowntweetembed-0.1.dist-info/WHEEL
markdowntweetembed-0.1.dist-info/top_level.txt
markdowntweetembed-0.1.dist-info/RECORD
